{"floors":{"floors":[{"k":[60,0,0,80,0],"v":{"t":[0,0,1,1]}},{"k":[59,0,0,81,0],"v":{"t":[0,0,1,1]}},{"k":[58,0,0,82,0],"v":{"t":[0,0,1,1]}},{"k":[57,0,0,83,0],"v":{"t":[0,0,1,1]}},{"k":[56,0,0,84,0],"v":{"t":[0,0,1,1]}},{"k":[55,0,0,85,0],"v":{"t":[0,0,1,1]}},{"k":[54,0,0,86,0],"v":{"t":[0,0,1,1]}},{"k":[53,0,0,87,0],"v":{"t":[0,0,1,1]}},{"k":[52,0,0,88,0],"v":{"t":[0,0,1,1]}},{"k":[51,0,0,89,0],"v":{"t":[0,0,1,1]}},{"k":[50,0,0,90,0],"v":{"t":[0,0,1,1]}},{"k":[49,0,0,91,0],"v":{"t":[0,0,1,1]}},{"k":[48,0,0,92,0],"v":{"t":[0,0,1,1]}},{"k":[61,0,0,80,0],"v":{"t":[0,0,1,1]}},{"k":[60,0,0,81,0],"v":{"t":[0,0,1,1]}},{"k":[59,0,0,82,0],"v":{"t":[0,0,1,1]}},{"k":[58,0,0,83,0],"v":{"t":[0,0,1,1]}},{"k":[57,0,0,84,0],"v":{"t":[0,0,1,1]}},{"k":[56,0,0,85,0],"v":{"t":[0,0,1,1]}},{"k":[55,0,0,86,0],"v":{"t":[0,0,1,1]}},{"k":[54,0,0,87,0],"v":{"t":[0,0,1,1]}},{"k":[53,0,0,88,0],"v":{"t":[0,0,1,1]}},{"k":[52,0,0,89,0],"v":{"t":[0,0,1,1]}},{"k":[51,0,0,90,0],"v":{"t":[0,0,1,1]}},{"k":[50,0,0,91,0],"v":{"t":[0,0,1,1]}},{"k":[49,0,0,92,0],"v":{"t":[0,0,1,1]}},{"k":[48,0,0,93,0],"v":{"t":[0,0,1,1]}},{"k":[62,0,0,80,0],"v":{"t":[0,0,1,1]}},{"k":[61,0,0,81,0],"v":{"t":[0,0,1,1]}},{"k":[60,0,0,82,0],"v":{"t":[0,0,1,1]}},{"k":[59,0,0,83,0],"v":{"t":[0,0,1,1]}},{"k":[58,0,0,84,0],"v":{"t":[0,0,1,1]}},{"k":[57,0,0,85,0],"v":{"t":[0,0,1,1]}},{"k":[56,0,0,86,0],"v":{"t":[0,0,1,1]}},{"k":[55,0,0,87,0],"v":{"t":[0,0,1,1]}},{"k":[54,0,0,88,0],"v":{"t":[0,0,1,1]}},{"k":[53,0,0,89,0],"v":{"t":[0,0,1,1]}},{"k":[52,0,0,90,0],"v":{"t":[0,0,1,1]}},{"k":[51,0,0,91,0],"v":{"t":[0,0,1,1]}},{"k":[50,0,0,92,0],"v":{"t":[0,0,1,1]}},{"k":[49,0,0,93,0],"v":{"t":[0,0,1,1]}},{"k":[48,0,0,94,0],"v":{"t":[0,0,1,1]}},{"k":[63,0,0,80,0],"v":{"t":[0,0,1,1]}},{"k":[62,0,0,81,0],"v":{"t":[0,0,1,1]}},{"k":[61,0,0,82,0],"v":{"t":[0,0,1,1]}},{"k":[60,0,0,83,0],"v":{"t":[0,0,1,1]}},{"k":[59,0,0,84,0],"v":{"t":[0,0,1,1]}},{"k":[58,0,0,85,0],"v":{"t":[0,0,1,1]}},{"k":[57,0,0,86,0],"v":{"t":[0,0,1,1]}},{"k":[56,0,0,87,0],"v":{"t":[0,0,1,1]}},{"k":[55,0,0,88,0],"v":{"t":[0,0,1,1]}},{"k":[54,0,0,89,0],"v":{"t":[0,0,1,1]}},{"k":[53,0,0,90,0],"v":{"t":[0,0,1,1]}},{"k":[52,0,0,91,0],"v":{"t":[0,0,1,1]}},{"k":[51,0,0,92,0],"v":{"t":[0,0,1,1]}},{"k":[50,0,0,93,0],"v":{"t":[0,0,1,1]}},{"k":[49,0,0,94,0],"v":{"t":[0,0,1,1]}},{"k":[48,0,0,95,0],"v":{"t":[0,0,1,1]}},{"k":[56,0,0,80,0],"v":{"t":[0,0,1,1]}},{"k":[55,0,0,81,0],"v":{"t":[0,0,1,1]}},{"k":[54,0,0,82,0],"v":{"t":[0,0,1,1]}},{"k":[53,0,0,83,0],"v":{"t":[0,0,1,1]}},{"k":[52,0,0,84,0],"v":{"t":[0,0,1,1]}},{"k":[51,0,0,85,0],"v":{"t":[0,0,1,1]}},{"k":[50,0,0,86,0],"v":{"t":[0,0,1,1]}},{"k":[49,0,0,87,0],"v":{"t":[0,0,1,1]}},{"k":[48,0,0,88,0],"v":{"t":[0,0,1,1]}},{"k":[57,0,0,80,0],"v":{"t":[0,0,1,1]}},{"k":[56,0,0,81,0],"v":{"t":[0,0,1,1]}},{"k":[55,0,0,82,0],"v":{"t":[0,0,1,1]}},{"k":[54,0,0,83,0],"v":{"t":[0,0,1,1]}},{"k":[53,0,0,84,0],"v":{"t":[0,0,1,1]}},{"k":[52,0,0,85,0],"v":{"t":[0,0,1,1]}},{"k":[51,0,0,86,0],"v":{"t":[0,0,1,1]}},{"k":[50,0,0,87,0],"v":{"t":[0,0,1,1]}},{"k":[49,0,0,88,0],"v":{"t":[0,0,1,1]}},{"k":[48,0,0,89,0],"v":{"t":[0,0,1,1]}},{"k":[58,0,0,80,0],"v":{"t":[0,0,1,1]}},{"k":[57,0,0,81,0],"v":{"t":[0,0,1,1]}},{"k":[56,0,0,82,0],"v":{"t":[0,0,1,1]}},{"k":[55,0,0,83,0],"v":{"t":[0,0,1,1]}},{"k":[54,0,0,84,0],"v":{"t":[0,0,1,1]}},{"k":[53,0,0,85,0],"v":{"t":[0,0,1,1]}},{"k":[52,0,0,86,0],"v":{"t":[0,0,1,1]}},{"k":[51,0,0,87,0],"v":{"t":[0,0,1,1]}},{"k":[50,0,0,88,0],"v":{"t":[0,0,1,1]}},{"k":[49,0,0,89,0],"v":{"t":[0,0,1,1]}},{"k":[48,0,0,90,0],"v":{"t":[0,0,1,1]}},{"k":[59,0,0,80,0],"v":{"t":[0,0,1,1]}},{"k":[58,0,0,81,0],"v":{"t":[0,0,1,1]}},{"k":[57,0,0,82,0],"v":{"t":[0,0,1,1]}},{"k":[56,0,0,83,0],"v":{"t":[0,0,1,1]}},{"k":[55,0,0,84,0],"v":{"t":[0,0,1,1]}},{"k":[54,0,0,85,0],"v":{"t":[0,0,1,1]}},{"k":[53,0,0,86,0],"v":{"t":[0,0,1,1]}},{"k":[52,0,0,87,0],"v":{"t":[0,0,1,1]}},{"k":[51,0,0,88,0],"v":{"t":[0,0,1,1]}},{"k":[50,0,0,89,0],"v":{"t":[0,0,1,1]}},{"k":[49,0,0,90,0],"v":{"t":[0,0,1,1]}},{"k":[48,0,0,91,0],"v":{"t":[0,0,1,1]}},{"k":[52,0,0,80,0],"v":{"t":[0,0,1,1]}},{"k":[51,0,0,81,0],"v":{"t":[0,0,1,1]}},{"k":[50,0,0,82,0],"v":{"t":[0,0,1,1]}},{"k":[49,0,0,83,0],"v":{"t":[0,0,1,1]}},{"k":[48,0,0,84,0],"v":{"t":[0,0,1,1]}},{"k":[53,0,0,80,0],"v":{"t":[0,0,1,1]}},{"k":[52,0,0,81,0],"v":{"t":[0,0,1,1]}},{"k":[51,0,0,82,0],"v":{"t":[0,0,1,1]}},{"k":[50,0,0,83,0],"v":{"t":[0,0,1,1]}},{"k":[49,0,0,84,0],"v":{"t":[0,0,1,1]}},{"k":[48,0,0,85,0],"v":{"t":[0,0,1,1]}},{"k":[54,0,0,80,0],"v":{"t":[0,0,1,1]}},{"k":[53,0,0,81,0],"v":{"t":[0,0,1,1]}},{"k":[52,0,0,82,0],"v":{"t":[0,0,1,1]}},{"k":[51,0,0,83,0],"v":{"t":[0,0,1,1]}},{"k":[50,0,0,84,0],"v":{"t":[0,0,1,1]}},{"k":[49,0,0,85,0],"v":{"t":[0,0,1,1]}},{"k":[48,0,0,86,0],"v":{"t":[0,0,1,1]}},{"k":[55,0,0,80,0],"v":{"t":[0,0,1,1]}},{"k":[54,0,0,81,0],"v":{"t":[0,0,1,1]}},{"k":[53,0,0,82,0],"v":{"t":[0,0,1,1]}},{"k":[52,0,0,83,0],"v":{"t":[0,0,1,1]}},{"k":[51,0,0,84,0],"v":{"t":[0,0,1,1]}},{"k":[50,0,0,85,0],"v":{"t":[0,0,1,1]}},{"k":[49,0,0,86,0],"v":{"t":[0,0,1,1]}},{"k":[48,0,0,87,0],"v":{"t":[0,0,1,1]}},{"k":[48,0,0,80,0],"v":{"t":[0,0,1,1]}},{"k":[49,0,0,80,0],"v":{"t":[0,0,1,1]}},{"k":[48,0,0,81,0],"v":{"t":[0,0,1,1]}},{"k":[50,0,0,80,0],"v":{"t":[0,0,1,1]}},{"k":[49,0,0,81,0],"v":{"t":[0,0,1,1]}},{"k":[48,0,0,82,0],"v":{"t":[0,0,1,1]}},{"k":[51,0,0,80,0],"v":{"t":[0,0,1,1]}},{"k":[50,0,0,81,0],"v":{"t":[0,0,1,1]}},{"k":[49,0,0,82,0],"v":{"t":[0,0,1,1]}},{"k":[48,0,0,83,0],"v":{"t":[0,0,1,1]}},{"k":[63,0,0,93,0],"v":{"t":[0,0,1,1]}},{"k":[62,0,0,94,0],"v":{"t":[0,0,1,1]}},{"k":[61,0,0,95,0],"v":{"t":[0,0,1,1]}},{"k":[63,0,0,94,0],"v":{"t":[0,0,1,1]}},{"k":[62,0,0,95,0],"v":{"t":[0,0,1,1]}},{"k":[63,0,0,95,0],"v":{"t":[0,0,1,1]}},{"k":[63,0,0,89,0],"v":{"t":[0,0,1,1]}},{"k":[62,0,0,90,0],"v":{"t":[0,0,1,1]}},{"k":[61,0,0,91,0],"v":{"t":[0,0,1,1]}},{"k":[60,0,0,92,0],"v":{"t":[0,0,1,1]}},{"k":[59,0,0,93,0],"v":{"t":[0,0,1,1]}},{"k":[58,0,0,94,0],"v":{"t":[0,0,1,1]}},{"k":[57,0,0,95,0],"v":{"t":[0,0,1,1]}},{"k":[63,0,0,90,0],"v":{"t":[0,0,1,1]}},{"k":[62,0,0,91,0],"v":{"t":[0,0,1,1]}},{"k":[61,0,0,92,0],"v":{"t":[0,0,1,1]}},{"k":[60,0,0,93,0],"v":{"t":[0,0,1,1]}},{"k":[59,0,0,94,0],"v":{"t":[0,0,1,1]}},{"k":[58,0,0,95,0],"v":{"t":[0,0,1,1]}},{"k":[63,0,0,91,0],"v":{"t":[0,0,1,1]}},{"k":[62,0,0,92,0],"v":{"t":[0,0,1,1]}},{"k":[61,0,0,93,0],"v":{"t":[0,0,1,1]}},{"k":[60,0,0,94,0],"v":{"t":[0,0,1,1]}},{"k":[59,0,0,95,0],"v":{"t":[0,0,1,1]}},{"k":[63,0,0,92,0],"v":{"t":[0,0,1,1]}},{"k":[62,0,0,93,0],"v":{"t":[0,0,1,1]}},{"k":[61,0,0,94,0],"v":{"t":[0,0,1,1]}},{"k":[60,0,0,95,0],"v":{"t":[0,0,1,1]}},{"k":[63,0,0,85,0],"v":{"t":[0,0,1,1]}},{"k":[62,0,0,86,0],"v":{"t":[0,0,1,1]}},{"k":[61,0,0,87,0],"v":{"t":[0,0,1,1]}},{"k":[60,0,0,88,0],"v":{"t":[0,0,1,1]}},{"k":[59,0,0,89,0],"v":{"t":[0,0,1,1]}},{"k":[58,0,0,90,0],"v":{"t":[0,0,1,1]}},{"k":[57,0,0,91,0],"v":{"t":[0,0,1,1]}},{"k":[56,0,0,92,0],"v":{"t":[0,0,1,1]}},{"k":[55,0,0,93,0],"v":{"t":[0,0,1,1]}},{"k":[54,0,0,94,0],"v":{"t":[0,0,1,1]}},{"k":[53,0,0,95,0],"v":{"t":[0,0,1,1]}},{"k":[63,0,0,86,0],"v":{"t":[0,0,1,1]}},{"k":[62,0,0,87,0],"v":{"t":[0,0,1,1]}},{"k":[61,0,0,88,0],"v":{"t":[0,0,1,1]}},{"k":[60,0,0,89,0],"v":{"t":[0,0,1,1]}},{"k":[59,0,0,90,0],"v":{"t":[0,0,1,1]}},{"k":[58,0,0,91,0],"v":{"t":[0,0,1,1]}},{"k":[57,0,0,92,0],"v":{"t":[0,0,1,1]}},{"k":[56,0,0,93,0],"v":{"t":[0,0,1,1]}},{"k":[55,0,0,94,0],"v":{"t":[0,0,1,1]}},{"k":[54,0,0,95,0],"v":{"t":[0,0,1,1]}},{"k":[63,0,0,87,0],"v":{"t":[0,0,1,1]}},{"k":[62,0,0,88,0],"v":{"t":[0,0,1,1]}},{"k":[61,0,0,89,0],"v":{"t":[0,0,1,1]}},{"k":[60,0,0,90,0],"v":{"t":[0,0,1,1]}},{"k":[59,0,0,91,0],"v":{"t":[0,0,1,1]}},{"k":[58,0,0,92,0],"v":{"t":[0,0,1,1]}},{"k":[57,0,0,93,0],"v":{"t":[0,0,1,1]}},{"k":[56,0,0,94,0],"v":{"t":[0,0,1,1]}},{"k":[55,0,0,95,0],"v":{"t":[0,0,1,1]}},{"k":[63,0,0,88,0],"v":{"t":[0,0,1,1]}},{"k":[62,0,0,89,0],"v":{"t":[0,0,1,1]}},{"k":[61,0,0,90,0],"v":{"t":[0,0,1,1]}},{"k":[60,0,0,91,0],"v":{"t":[0,0,1,1]}},{"k":[59,0,0,92,0],"v":{"t":[0,0,1,1]}},{"k":[58,0,0,93,0],"v":{"t":[0,0,1,1]}},{"k":[57,0,0,94,0],"v":{"t":[0,0,1,1]}},{"k":[56,0,0,95,0],"v":{"t":[0,0,1,1]}},{"k":[63,0,0,81,0],"v":{"t":[0,0,1,1]}},{"k":[62,0,0,82,0],"v":{"t":[0,0,1,1]}},{"k":[61,0,0,83,0],"v":{"t":[0,0,1,1]}},{"k":[60,0,0,84,0],"v":{"t":[0,0,1,1]}},{"k":[59,0,0,85,0],"v":{"t":[0,0,1,1]}},{"k":[58,0,0,86,0],"v":{"t":[0,0,1,1]}},{"k":[57,0,0,87,0],"v":{"t":[0,0,1,1]}},{"k":[56,0,0,88,0],"v":{"t":[0,0,1,1]}},{"k":[55,0,0,89,0],"v":{"t":[0,0,1,1]}},{"k":[54,0,0,90,0],"v":{"t":[0,0,1,1]}},{"k":[53,0,0,91,0],"v":{"t":[0,0,1,1]}},{"k":[52,0,0,92,0],"v":{"t":[0,0,1,1]}},{"k":[51,0,0,93,0],"v":{"t":[0,0,1,1]}},{"k":[50,0,0,94,0],"v":{"t":[0,0,1,1]}},{"k":[49,0,0,95,0],"v":{"t":[0,0,1,1]}},{"k":[63,0,0,82,0],"v":{"t":[0,0,1,1]}},{"k":[62,0,0,83,0],"v":{"t":[0,0,1,1]}},{"k":[61,0,0,84,0],"v":{"t":[0,0,1,1]}},{"k":[60,0,0,85,0],"v":{"t":[0,0,1,1]}},{"k":[59,0,0,86,0],"v":{"t":[0,0,1,1]}},{"k":[58,0,0,87,0],"v":{"t":[0,0,1,1]}},{"k":[57,0,0,88,0],"v":{"t":[0,0,1,1]}},{"k":[56,0,0,89,0],"v":{"t":[0,0,1,1]}},{"k":[55,0,0,90,0],"v":{"t":[0,0,1,1]}},{"k":[54,0,0,91,0],"v":{"t":[0,0,1,1]}},{"k":[53,0,0,92,0],"v":{"t":[0,0,1,1]}},{"k":[52,0,0,93,0],"v":{"t":[0,0,1,1]}},{"k":[51,0,0,94,0],"v":{"t":[0,0,1,1]}},{"k":[50,0,0,95,0],"v":{"t":[0,0,1,1]}},{"k":[63,0,0,83,0],"v":{"t":[0,0,1,1]}},{"k":[62,0,0,84,0],"v":{"t":[0,0,1,1]}},{"k":[61,0,0,85,0],"v":{"t":[0,0,1,1]}},{"k":[60,0,0,86,0],"v":{"t":[0,0,1,1]}},{"k":[59,0,0,87,0],"v":{"t":[0,0,1,1]}},{"k":[58,0,0,88,0],"v":{"t":[0,0,1,1]}},{"k":[57,0,0,89,0],"v":{"t":[0,0,1,1]}},{"k":[56,0,0,90,0],"v":{"t":[0,0,1,1]}},{"k":[55,0,0,91,0],"v":{"t":[0,0,1,1]}},{"k":[54,0,0,92,0],"v":{"t":[0,0,1,1]}},{"k":[53,0,0,93,0],"v":{"t":[0,0,1,1]}},{"k":[52,0,0,94,0],"v":{"t":[0,0,1,1]}},{"k":[51,0,0,95,0],"v":{"t":[0,0,1,1]}},{"k":[63,0,0,84,0],"v":{"t":[0,0,1,1]}},{"k":[62,0,0,85,0],"v":{"t":[0,0,1,1]}},{"k":[61,0,0,86,0],"v":{"t":[0,0,1,1]}},{"k":[60,0,0,87,0],"v":{"t":[0,0,1,1]}},{"k":[59,0,0,88,0],"v":{"t":[0,0,1,1]}},{"k":[58,0,0,89,0],"v":{"t":[0,0,1,1]}},{"k":[57,0,0,90,0],"v":{"t":[0,0,1,1]}},{"k":[56,0,0,91,0],"v":{"t":[0,0,1,1]}},{"k":[55,0,0,92,0],"v":{"t":[0,0,1,1]}},{"k":[54,0,0,93,0],"v":{"t":[0,0,1,1]}},{"k":[53,0,0,94,0],"v":{"t":[0,0,1,1]}},{"k":[52,0,0,95,0],"v":{"t":[0,0,1,1]}}]},"objs":{"list":[]},"sprites":{"list":[]}}